<?xml version="1.0" encoding="utf-8" standalone="no"?>
<!DOCTYPE superEntry SYSTEM "2007nn.dtd">
<superEntry>
	<orth>병적</orth>
	<entry n="1" pos="nng_s">
		<mnt_grp>
			<cre>
				<cre_date>2003/10/16</cre_date>
				<cre_writer>한동훈</cre_writer>
			</cre>
			<mod>
				<mod_date>2003/10/16</mod_date>
				<mod_writer>한동훈</mod_writer>
			</mod>
			<mod>
				<mod_date>2004/10/03</mod_date>
				<mod_writer>이민우</mod_writer>
				<mod_note></mod_note>
			</mod>
			<mod>
				<mod_date>2007/09/20</mod_date>
				<mod_writer>김이정</mod_writer>
				<mod_note>n_v 기술</mod_note>
			</mod>
			<mod>
				<mod_date>2009/11/01</mod_date>
				<mod_writer>김민호</mod_writer>
				<mod_note>UTF-8로 변경, XML 태그 오류 수정</mod_note>
			</mod>
		</mnt_grp>
		<morph_grp>
			<org lg="si">兵籍</org>
		
			<hom exist="yes"/>
		</morph_grp>
		<idm_grp>
		</idm_grp>
		<sense n="1">
			<sem_grp>
				<eg>나는 ~으로서 남에게 피해가 되는 일을 하지 않을 것이다.</eg>
				<eg>기자들이 대통령의 ~을 조사했다.</eg>
				<trans>one's military status</trans>
				<sem_class>문서</sem_class>
				<lr>
				</lr>
			</sem_grp>
			<syn_grp>
				<comb_v type="narg_vpred">
					<form vcompound="no">~을 조사하다</form>
					<frame></frame>
				</comb_v>
				<cl type="uni"></cl>
			</syn_grp>
		</sense>
	</entry>
	<entry n="2" pos="nng_s">
		<mnt_grp>
			<cre>
				<cre_date>2003/10/16</cre_date>
				<cre_writer>한동훈</cre_writer>
			</cre>
			<mod>
				<mod_date>2003/10/16</mod_date>
				<mod_writer>한동훈</mod_writer>
			</mod>
			<mod>
				<mod_date>2004/10/03</mod_date>
				<mod_writer>이민우</mod_writer>
				<mod_note></mod_note>
			</mod>
			<mod>
				<mod_date>2007/09/20</mod_date>
				<mod_writer>김이정</mod_writer>
				<mod_note></mod_note>
			</mod>
			<mod>
				<mod_date>2009/11/01</mod_date>
				<mod_writer>김민호</mod_writer>
				<mod_note>UTF-8로 변경, XML 태그 오류 수정</mod_note>
			</mod>
		</mnt_grp>
		<morph_grp>
			<org lg="si">屛迹</org>
		
			<hom exist="yes"/>
		</morph_grp>
		<idm_grp>
		</idm_grp>
		<sense n="1">
			<sem_grp>
				<eg>나는 나도 모르게 바지에 오줌을 싸서 부끄러운 나머지 ~을 했다.</eg>
				<trans>disappear</trans>
				<sem_class>이동행위</sem_class>
				<lr>
				</lr>
			</sem_grp>
			<syn_grp>
				<comb_v type="npred_vsup">
					<form vcompound="yes">~을 하다</form>
					<frame>X-이 Y-에 ~을 하다</frame>
				</comb_v>
				<sel_rst arg="X">인간|인간집단</sel_rst>
				<sel_rst arg="Y">장소</sel_rst>
				<cl type="uni">번</cl>
				<cl type="uni">회</cl>
				<cl type="uni">차례</cl>
			</syn_grp>
		</sense>
	</entry>
	<entry n="3" pos="nng_s">
		<mnt_grp>
			<cre>
				<cre_date>2003/10/16</cre_date>
				<cre_writer>한동훈</cre_writer>
			</cre>
			<mod>
				<mod_date>2003/10/16</mod_date>
				<mod_writer>한동훈</mod_writer>
			</mod>
			<mod>
				<mod_date>2004/10/03</mod_date>
				<mod_writer>이민우</mod_writer>
				<mod_note>의존적으로만 쓰임</mod_note>
			</mod>
			<mod>
				<mod_date>2007/09/20</mod_date>
				<mod_writer>김이정</mod_writer>
				<mod_note></mod_note>
			</mod>
			<mod>
				<mod_date>2009/11/01</mod_date>
				<mod_writer>김민호</mod_writer>
				<mod_note>UTF-8로 변경, XML 태그 오류 수정</mod_note>
			</mod>
		</mnt_grp>
		<morph_grp>
			<org lg="si">病的</org>
		
			<hom exist="yes"/>
		</morph_grp>
		<idm_grp>
			<idm type="etc">~으로</idm>
		</idm_grp>
		<sense n="1">
			<sem_grp>
				<eg>난 ~으로 망가지고 있는 중이었다.</eg>
				<trans>diseased</trans>
				<trans>abnormal</trans>
				<sem_class>신체상태</sem_class>
				<lr>
				</lr>
			</sem_grp>
			<syn_grp>
			</syn_grp>
		</sense>
	</entry>
</superEntry>
