<?xml version="1.0" encoding="utf-8" standalone="no"?>
<!DOCTYPE superEntry SYSTEM "2007nn.dtd">

<superEntry>
	<orth>불명</orth>
	<entry n="1" pos="nng_s">
		<mnt_grp>
			<cre>
				<cre_date>2002/08/18</cre_date>
				<cre_writer>남길임</cre_writer>
				<cre_note></cre_note>
			</cre>
			<mod>
				<mod_date>2003/09/16</mod_date>
				<mod_writer>박진호</mod_writer>
				<mod_note></mod_note>
			</mod>
			<mod>
				<mod_date>2005/09/15</mod_date>
				<mod_writer>이광호</mod_writer>
				<mod_note></mod_note>
			</mod>
			<mod>
				<mod_date>2005/10/11</mod_date>
				<mod_writer>김이정</mod_writer>
				<mod_note>n_n, 선택제약 추가</mod_note>
			</mod>
			<mod>
				<mod_date>2007/10/10</mod_date>
				<mod_writer>김이정</mod_writer>
				<mod_note></mod_note>
			</mod>
			<note>2002/08/18(남길임)</note>
			<note>2002/08/18(이병규)</note>
			<note>2003/07/16(류희선)대역어 검토요망(적합한 명사형이 없어 기존의 것을 그대로 둠)</note>
			<note>2003/09/16(박진호)격틀, 선택제약, 명사연어 추가</note>
			<note>대역어 정보의 문제: 특정 명사의 경우, 특히 조사 결합에 제약이 있는 경우 명사형 대역어가 적합하지 않은 경우 있음.</note>
			<add></add>
			<mod>
				<mod_date>2009/11/01</mod_date>
				<mod_writer>김민호</mod_writer>
				<mod_note>UTF-8로 변경, XML 태그 오류 수정</mod_note>
			</mod>
		</mnt_grp>
		<see></see>
		<morph_grp>
			<var type="temp"></var>
			<str type="temp"></str>
			<org lg="si">不明</org>
		
			<hom exist="temp"></hom>
			<der pos="temp" type="temp"></der>
			<comp pos="temp" type="temp"></comp>
			<metc pos="temp" type="temp"></metc>
			<img type="temp"></img>
		</morph_grp>
		<idm_grp>
			<idm type="temp"></idm>
		</idm_grp>
		<sense n="1">
			<sem_grp>
				<eg>어느날 나는 발신자 ~의 편지를 하나 받았다.</eg>
				<trans>unidentified</trans>
				<domain></domain>
				<reg></reg>
				<con></con>
				<sem_class>상태</sem_class>
				<lr>
					<syn type="temp"></syn>
					<ant type="temp"></ant>
					<rel></rel>
				</lr>
			</sem_grp>
			<syn_grp>
				<comb_aj type="temp"></comb_aj>
				<comb_n type="compound">수취인 ~</comb_n>
				<comb_n type="compound">소재지 ~</comb_n>
				<comb_n type="compound">국적 ~</comb_n>
				<comb_n type="compound">원인 ~</comb_n>
				<comb_v type="npred_vsup">
					<form vcompound="yes">~이다</form>
					<frame>X-이 ~이다</frame>
				</comb_v>
				<max_n_str></max_n_str>
				<sel_rst arg="X">추상적대상|수동적행위인간|인간관계장소</sel_rst>
				<cl type="temp"></cl>
				<prt></prt>
				<av></av>
				<pre_d/>
				<pre_n/>
				<s_n/>
			</syn_grp>
		</sense>
	</entry>
</superEntry>
