<?xml version="1.0" encoding="utf-8" standalone="no"?>
<!DOCTYPE superEntry SYSTEM "2007nn.dtd">
<superEntry>
	<orth>불통</orth>
	<entry n="1" pos="nng_s">
		<mnt_grp>
			<cre>
				<cre_date>2003/10/25</cre_date>
				<cre_writer>한동훈</cre_writer>
			</cre>
			<mod>
				<mod_date>2003/10/28</mod_date>
				<mod_writer>한동훈</mod_writer>
			</mod>
			<mod>
				<mod_date>2004/10/03</mod_date>
				<mod_writer>이민우</mod_writer>
				<mod_note></mod_note>
			</mod>
			<mod>
				<mod_date>2004/12/24</mod_date>
				<mod_writer>고길수</mod_writer>
				<mod_note>논항명사구 추가</mod_note>
				<mod_note>논항 의미정보 수정</mod_note>
				<mod_note></mod_note>
			</mod>
			<mod>
				<mod_date>2009/11/01</mod_date>
				<mod_writer>김민호</mod_writer>
				<mod_note>UTF-8로 변경, XML 태그 오류 수정</mod_note>
			</mod>
		</mnt_grp>
		<morph_grp>
			<org lg="si">不通</org>
		
		</morph_grp>
		<idm_grp>
		</idm_grp>
		<sense n="1">
			<sem_grp>
				<eg>전화의 ~으로 다음날 아침까지 기다려야만 했다.</eg>
				<trans>interruption</trans>
				<sem_class>고장</sem_class> <!-- 사건의 술어들과 결합하지 않는듯 -->
				<lr>
				</lr>
			</sem_grp>
			<syn_grp>
				<comb_v type="npred_vsup">
					<form vcompound="yes">~이 되다</form>
					<frame>X-이 ~이 되다</frame>
				</comb_v>
				<max_n_str>X-의 ~</max_n_str> <!-- 추가함 -->
				<sel_rst arg="X">기계|시설망|교통기관</sel_rst> <!-- 교통|통신 수정 -->
				<cl type="uni">번</cl>
				<cl type="uni">회</cl>
				<cl type="uni">차례</cl>
			</syn_grp>
		</sense>
	</entry>
</superEntry>
