<?xml version="1.0" encoding="utf-8" standalone="no"?>
<!DOCTYPE superEntry SYSTEM "2007nn.dtd">

<superEntry>
	<orth>육교</orth>
	<entry n="1" pos="nng_s">
		<mnt_grp>
			<cre>
				<cre_date>2000/08/19</cre_date>
				<cre_writer>이호승</cre_writer>
				<cre_note></cre_note>
			</cre>
			<mod>
				<mod_date>2003/01/09</mod_date>
				<mod_writer>고길수</mod_writer>
				<mod_note></mod_note>
			</mod>
			<mod>
				<mod_date>2006/09/25</mod_date>
				<mod_writer>전미현</mod_writer>
				<mod_note></mod_note>
			</mod>
			<mod>
				<mod_date>2007/09/04</mod_date>
				<mod_writer>권오희</mod_writer>
				<mod_note></mod_note>
			</mod>
			<note>2000/10/08(박동호)</note>
			<note>2002/12/27(한동훈)동사자유구성을add로 옮김</note>
			<note>2003/01/09(고길수)예문 추가</note>
			<note>의미부류를 '조형물'에서 '다리'로 수정</note>
			<note>의미부류수정</note>
			<mod>
				<mod_date>2009/11/01</mod_date>
				<mod_writer>김민호</mod_writer>
				<mod_note>UTF-8로 변경, XML 태그 오류 수정</mod_note>
			</mod>
			</mnt_grp>
		<see></see>
		<morph_grp>
			<var type="temp"></var>
			<str type="temp"></str>
			<org lg="si">陸橋</org>
		
			<hom exist="temp"></hom>
			<der pos="n" type="suffix">~설</der>
			<comp pos="temp" type="temp"></comp>
			<metc pos="temp" type="temp"></metc>
			<img type="temp"></img>
		</morph_grp>
		<idm_grp>
			<idm type="temp"></idm>
		</idm_grp>
		<sense n="1">
			<sem_grp>
				<eg>어느 거지가 ~ 에 누워 있었다.사람들은 ~를 건너기 시작했다.</eg>
				<trans>overpassfootbridge</trans>
				<domain></domain>
				<reg></reg>
				<con></con>
				<curs type="C"/>
				<sem_class>다리</sem_class>
				<lr>
					<syn type="temp"></syn>
					<ant type="temp"></ant>
					<hyper>다리</hyper>
					<coord>구름다리</coord>
					<coord>대교</coord>
					<coord>철교</coord>
					<rel></rel>
				</lr>
			</sem_grp>
			<syn_grp>
				<comb_aj type="temp"></comb_aj>
				<comb_n type="temp"></comb_n>
				<comb_v type="narg_vpred">
					<form vcompound="no">~를 건너다</form>
					<frame>X-이 ~를 건너다</frame>
				</comb_v>
				<comb_v type="narg_vpred">
					<form vcompound="no">~를 놓다</form>
					<frame>X- 이 Y-에 ~를 놓다</frame>
				</comb_v>
				<comb_v type="narg_vpred">
					<form vcompound="no">~를 세우다</form>
					<frame>X-이 Y-에 ~를 세우다</frame>
				</comb_v>
				<comb_v type="narg_vpred">
					<form vcompound="no">~를 지나다</form>
					<frame>X-이 ~를 지나다</frame>
				</comb_v>
				<max_n_str></max_n_str>
				<sel_rst arg="X">인간||인간집단</sel_rst>
				<sel_rst arg="Y">장소</sel_rst>
				<cl type="uni">개</cl>
				<prt></prt>
				<av></av>
				<pre_d/>
				<pre_n/>
				<s_n/>
			</syn_grp>
		</sense>
	</entry>
</superEntry>
