<?xml version="1.0" encoding="utf-8" standalone="no"?>
<!DOCTYPE superEntry SYSTEM "2007nn.dtd">




<superEntry>
	<orth>잔</orth>
	<entry n="1" pos="nng_s">
		<mnt_grp>
			<cre>
				<cre_date>2001/04/06</cre_date>
				<cre_writer>고길수</cre_writer>
				<cre_note></cre_note>
			</cre>
			<mod>
				<mod_date>2003/02/08</mod_date>
				<mod_writer>이지영</mod_writer>
				<mod_note></mod_note>
			</mod>
			<mod>
				<mod_date>2005/08/30</mod_date>
				<mod_writer>신선옥</mod_writer>
				<mod_note>add를 comb_v로 이동</mod_note>
			</mod>
			<mod>
				<mod_date>2007/08/05</mod_date>
				<mod_writer>김성용</mod_writer>
				<mod_note></mod_note>
			</mod>
			<note>2001/07/21(김종명)</note>
			<note>센스1과 2가 차이가 있나?</note>
			<note>숙어관용구획에서 '~을 드리다,비우다,올리다'를 동사자유구성으로</note>
			<note>숙어관용구획의 기타유형 항목에 '패배의 쓴 ~'을 추가</note>
			<note>단위표현에 '세트' 추가</note>
			<note>2001/07/30(김종명,이성헌)</note>
			<note>동의어에 '컵' 추가</note>
			<note>2003/01/30(이지영)문장부호입력,예문추가, comb_v를 add로 이동, hom수정</note>
			<note>2003/02/05(김진형)cl에 '벌' 추가</note>
			<note>2003/02/08(이지영)</note>
			<mod>
				<mod_date>2009/11/01</mod_date>
				<mod_writer>김민호</mod_writer>
				<mod_note>UTF-8로 변경, XML 태그 오류 수정</mod_note>
			</mod>
		</mnt_grp>
		<see></see>
		<morph_grp>
			<var type="temp"></var>
			<str type="temp"></str>
			<org lg="si">盞</org>
		
			<hom exist="yes"></hom>
			<der pos="temp" type="temp"></der>
			<comp pos="n" type="suffix">~받침</comp>
			<comp pos="n" type="prefix">술~</comp>
			<comp pos="n" type="prefix">물~</comp>
			<comp pos="n" type="prefix">찻~</comp>
			<comp pos="n" type="prefix">커피~</comp>
			<comp pos="n" type="prefix">맥주~</comp>
			<comp pos="n" type="prefix">소주~</comp>
			<comp pos="n" type="prefix">유리~</comp>
			<metc pos="temp" type="temp"></metc>
			<img type="temp"></img>
		</morph_grp>
		<idm_grp>
			<idm type="temp"></idm>
		</idm_grp>
		<sense n="1">
			<sem_grp>
				<eg>그는 ~에 물을 가득 따라 마셨다.</eg>
				<eg>실수로 ~을 깨뜨렸다.</eg>
				<trans>cup</trans>
				<trans>glass</trans>
				<domain></domain>
				<reg></reg>
				<con></con>
				<curs type="C"/>
				<sem_class>용기</sem_class>
				<lr>
					<syn type="etc">컵</syn>
					<ant type="temp"></ant>
					<hypo>술</hypo>
					<hypo>물</hypo>
					<hypo>찻</hypo>
					<hypo>커피</hypo>
					<hypo>유리</hypo>
					<hypo>맥주</hypo>
					<hypo>소주~</hypo>
					<coord>~받침</coord>
					<mero>손잡이</mero>
					<rel>물</rel>
					<rel>음료수</rel>
					<rel>술</rel>
				</lr>
			</sem_grp>
			<syn_grp>
				<comb_aj type="magn">~이 크다</comb_aj>
				<comb_aj type="min">~이 작다</comb_aj>
				<comb_n type="temp"></comb_n>
				<comb_v type="narg_vpred">
					<form vcompound="no">~에 따르다</form>
					<frame></frame>
				</comb_v>
				<comb_v type="narg_vpred">
					<form vcompound="no">~에 붓다</form>
					<frame></frame>
				</comb_v>
				<comb_v type="narg_vpred">
					<form vcompound="no">~에 채우다</form>
					<frame></frame>
				</comb_v>
				<comb_v type="narg_vpred">
					<form vcompound="no">~을 채우다</form>
					<frame></frame>
				</comb_v>
				<comb_v type="narg_vpred">
					<form vcompound="no">~을 들다</form>
					<frame></frame>
				</comb_v>
				<comb_v type="narg_vpred">
					<form vcompound="no">~을 깨다</form>
					<frame></frame>
				</comb_v>
				<comb_v type="narg_vpred">
					<form vcompound="no">~을 드리다</form>
					<frame></frame>
				</comb_v>
				<comb_v type="narg_vpred">
					<form vcompound="no">~을 비우다</form>
					<frame></frame>
				</comb_v>
				<comb_v type="narg_vpred">
					<form vcompound="no">~을 올리다</form>
					<frame></frame>
				</comb_v>
				<comb_v type="narg_vpred">
					<form vcompound="no">~을 부딪치다</form>
					<frame></frame>
				</comb_v>
				<comb_v type="narg_vpred">
					<form vcompound="no">~을 돌리다</form>
					<frame></frame>
				</comb_v>
				<comb_v type="narg_vpred">
					<form vcompound="no">~이 비다</form>
					<frame></frame>
				</comb_v>
				<max_n_str></max_n_str>
				<sel_rst arg="temp"></sel_rst>
				<cl type="uni">개</cl>
				<cl type="grp">세트</cl>
				<cl type="grp">벌</cl>
				<prt></prt>
				<av></av>
				<pre_d/>
				<pre_n/>
				<s_n/>
			</syn_grp>
		</sense>
	</entry>
</superEntry>
