<?xml version="1.0" encoding="utf-8" standalone="no"?>
<!DOCTYPE superEntry SYSTEM "2007nn.dtd">

<superEntry>
	<orth>정상</orth>
	<entry n="1" pos="nng_s">
		<mnt_grp>
			<cre>
				<cre_date>2000/07/19</cre_date>
				<cre_writer>신중진</cre_writer>
				<cre_note></cre_note>
			</cre>
			<mod>
				<mod_date>2003/03/31</mod_date>
				<mod_writer>이성헌</mod_writer>
				<mod_note></mod_note>
			</mod>
			<mod>
				<mod_date>2006/09/01</mod_date>
				<mod_writer>허영인</mod_writer>
				<mod_note></mod_note>
			</mod>
			<mod>
				<mod_date>2007/08/30</mod_date>
				<mod_writer>김성용</mod_writer>
				<mod_note></mod_note>
			</mod>
			<note>2000/09/07(박동호)</note>
			<note>2003/02/09(김성용)</note>
			<note>2003/03/31(이성헌)eg보완</note>
			<note>av에 '~(으로)'를 기재</note>
			<note>pre_N의 '~ 수업'을 add로 이동</note>
			<note>sem을 '긍정적인성'에서 '속성값'으로 수정</note>
			<note>supv와 sel_res기술</note>
			<add></add>
			<mod>
				<mod_date>2009/11/01</mod_date>
				<mod_writer>김민호</mod_writer>
				<mod_note>UTF-8로 변경, XML 태그 오류 수정</mod_note>
			</mod>
		</mnt_grp>
		<see></see>
		<morph_grp>
			<var type="temp"></var>
			<str type="temp"></str>
			<org lg="si">正常</org>
		
			<hom exist="yes"/>
			<der pos="n" type="suffix">~적</der>
			<der pos="n" type="suffix">~아</der>
			<der pos="n" type="suffix">~치</der>
			<der pos="n" type="suffix">~파</der>
			<der pos="n" type="suffix">~화</der>
			<der pos="n" type="prefix">비~</der>
			<comp pos="temp" type="temp"></comp>
			<metc pos="temp" type="temp"></metc>
			<img type="temp"></img>
		</morph_grp>
		<idm_grp>
			<idm type="da">~이다</idm>
			<idm type="etc">~에 우뚝 서다</idm>
		</idm_grp>
		<sense n="1">
			<sem_grp>
				<eg>그는 지금 ~이 아니다.현재 경제상황은 ~으로 판단된다.등락을 반복하던 증시가 마침내 ~을 되찾았다.</eg>
				<trans>normalcy</trans>
				<domain></domain>
				<reg></reg>
				<con></con>
				<curs type="U"/>
				<sem_class>속성값</sem_class>
				<lr>
					<syn type="temp"></syn>
					<ant type="etc">이상</ant>
					<rel></rel>
				</lr>
			</sem_grp>
			<syn_grp>
				<comb_aj type="temp"></comb_aj>
				<comb_n type="temp"></comb_n>
				<comb_v type="npred_vsup">
					<form vcompound="yes">~</form>
					<frame>X|S것-이 ~이다</frame>
				</comb_v>
				<max_n_str></max_n_str>
				<sel_rst arg="X">온</sel_rst>
				<cl type="temp"></cl>
				<prt></prt>
				<av>~</av>
				<av>~으로</av>
				<pre_d/>
				<pre_n/>
				<s_n/>
			</syn_grp>
		</sense>
	</entry>
	<entry n="2" pos="nng_s">
		<mnt_grp>
			<cre>
				<cre_date>2000/09/01</cre_date>
				<cre_writer>신중진</cre_writer>
				<cre_note></cre_note>
			</cre>
			<mod>
				<mod_date>2003/02/09</mod_date>
				<mod_writer>김성용</mod_writer>
				<mod_note></mod_note>
			</mod>
			<mod>
				<mod_date>2006/09/01</mod_date>
				<mod_writer>허영인</mod_writer>
				<mod_note></mod_note>
			</mod>
			<mod>
				<mod_date>2007/08/30</mod_date>
				<mod_writer>김성용</mod_writer>
				<mod_note></mod_note>
			</mod>
			<note>2000/09/07(박동호)</note>
			<note>2003/02/09(김성용)</note>
			<add></add>
			<mod>
				<mod_date>2009/11/01</mod_date>
				<mod_writer>김민호</mod_writer>
				<mod_note>UTF-8로 변경, XML 태그 오류 수정</mod_note>
			</mod>
		</mnt_grp>
		<see></see>
		<morph_grp>
			<var type="temp"></var>
			<str type="temp"></str>
			<org lg="si">情狀</org>
		
			<hom exist="yes"/>
			<der pos="temp" type="temp"></der>
			<comp pos="n" type="suffix">~참작</comp>
			<metc pos="temp" type="temp"></metc>
			<img type="temp"></img>
		</morph_grp>
		<idm_grp>
			<idm type="temp"></idm>
		</idm_grp>
		<sense n="1">
			<sem_grp>
				<eg>그의 가엾은 ~에 자못 동정이 간다.</eg>
				<trans></trans>
				<domain></domain>
				<reg></reg>
				<con></con>
				<curs type="U"/>
				<sem_class>상황</sem_class>
				<lr>
					<syn type="temp"></syn>
					<ant type="temp"></ant>
					<rel></rel>
				</lr>
			</sem_grp>
			<syn_grp>
				<comb_aj type="temp"></comb_aj>
				<comb_n type="temp"></comb_n>
				<comb_v type="narg_vpred">
					<form vcompound="no">~을 살피다</form>
					<frame></frame>
				</comb_v>
				<comb_v type="narg_vpred">
					<form vcompound="no">~을 고려하다</form>
					<frame></frame>
				</comb_v>
				<comb_v type="narg_vpred">
					<form vcompound="no">~을 참작하다</form>
					<frame></frame>
				</comb_v>
				<max_n_str></max_n_str>
				<sel_rst arg="temp"></sel_rst>
				<cl type="temp"></cl>
				<prt></prt>
				<av></av>
				<pre_d/>
				<pre_n/>
				<s_n/>
			</syn_grp>
		</sense>
	</entry>
	<entry n="3" pos="nng_s">
		<mnt_grp>
			<cre>
				<cre_date>2000/09/01</cre_date>
				<cre_writer>신중진</cre_writer>
				<cre_note></cre_note>
			</cre>
			<mod>
				<mod_date>2003/02/09</mod_date>
				<mod_writer>김성용</mod_writer>
				<mod_note></mod_note>
			</mod>
			<mod>
				<mod_date>2006/09/01</mod_date>
				<mod_writer>허영인</mod_writer>
				<mod_note></mod_note>
			</mod>
			<mod>
				<mod_date>2007/08/30</mod_date>
				<mod_writer>김성용</mod_writer>
				<mod_note></mod_note>
			</mod>
			<note>2000/09/07(박동호)</note>
			<note>2003/02/09(김성용)</note>
			<add>~에 오르다</add>
			<add>~에서 내려오다</add>
			<add>~에서 내려오다</add>
			<add>~을 지키다</add>
			<mod>
				<mod_date>2009/11/01</mod_date>
				<mod_writer>김민호</mod_writer>
				<mod_note>UTF-8로 변경, XML 태그 오류 수정</mod_note>
			</mod>
		</mnt_grp>
		<see></see>
		<morph_grp>
			<var type="temp"></var>
			<str type="temp"></str>
			<org lg="si">頂上</org>
		
			<hom exist="yes"/>
			<der pos="temp" type="temp"></der>
			<comp pos="temp" type="temp"></comp>
			<metc pos="temp" type="temp"></metc>
			<img type="temp"></img>
		</morph_grp>
		<idm_grp>
			<idm type="temp"></idm>
		</idm_grp>
		<sense n="1">
			<sem_grp>
				<eg>등정대가 고봉의 ~을 정복하였다.</eg>
				<trans></trans>
				<domain></domain>
				<reg></reg>
				<con></con>
				<curs type="C"/>
				<sem_class>구체물의부분</sem_class>
				<lr>
					<syn type="etc">꼭대기</syn>
					<ant type="etc">바닥</ant>
					<rel></rel>
				</lr>
			</sem_grp>
			<syn_grp>
				<comb_aj type="temp"></comb_aj>
				<comb_n type="temp"></comb_n>
				<comb_v type="narg_vpred">
					<form vcompound="no">~에 오르다</form>
					<frame></frame>
				</comb_v>
				<comb_v type="narg_vpred">
					<form vcompound="no">~에서 내려오다</form>
					<frame></frame>
				</comb_v>
				<comb_v type="narg_vpred">
					<form vcompound="no">~에서 내려오다</form>
					<frame></frame>
				</comb_v>
				<comb_v type="narg_vpred">
					<form vcompound="no">~을 지키다</form>
					<frame></frame>
				</comb_v>
				<max_n_str></max_n_str>
				<sel_rst arg="temp"></sel_rst>
				<cl type="temp"></cl>
				<prt></prt>
				<av></av>
				<pre_d/>
				<pre_n/>
				<s_n/>
			</syn_grp>
		</sense>
		<sense n="2">
			<sem_grp>
				<eg>그녀는 오랫동안 가요계의 ~을 지키고 있다.</eg>
				<trans></trans>
				<domain></domain>
				<reg></reg>
				<con></con>
				<curs type="U"/>
				<sem_class>높은정도</sem_class>
				<lr>
					<syn type="etc">지존</syn>
					<ant type="temp"></ant>
					<rel></rel>
				</lr>
			</sem_grp>
			<syn_grp>
				<comb_aj type="temp"></comb_aj>
				<comb_n type="compound">인기 ~</comb_n>
				<comb_n type="compound">~(의) 가수</comb_n>
				<comb_v type="narg_vpred">
					<form vcompound="no">~에 등극하다</form>
					<frame></frame>
				</comb_v>
				<comb_v type="narg_vpred">
					<form vcompound="no">~에 오르다</form>
					<frame></frame>
				</comb_v>
				<max_n_str></max_n_str>
				<sel_rst arg="temp"></sel_rst>
				<cl type="temp"></cl>
				<prt></prt>
				<av></av>
				<pre_d/>
				<pre_n/>
				<s_n/>
			</syn_grp>
		</sense>
		<sense n="3">
			<sem_grp>
				<eg>남북의 두 ~이 50년만에 만났다.</eg>
				<trans></trans>
				<domain></domain>
				<reg></reg>
				<con></con>
				<curs type="C"/>
				<sem_class>직위인간</sem_class>
				<lr>
					<syn type="temp"></syn>
					<ant type="temp"></ant>
					<rel></rel>
				</lr>
			</sem_grp>
			<syn_grp>
				<comb_aj type="temp"></comb_aj>
				<comb_n type="compound">~ 회담</comb_n>
				<comb_v type="temp">
					<form vcompound="temp"></form>
					<frame></frame>
				</comb_v>
				<max_n_str></max_n_str>
				<sel_rst arg="temp"></sel_rst>
				<cl type="uni">명</cl>
				<cl type="uni">인</cl>
				<prt></prt>
				<av></av>
				<pre_d/>
				<pre_n/>
				<s_n/>
			</syn_grp>
		</sense>
	</entry>
</superEntry>
