<?xml version="1.0" encoding="utf-8" standalone="no"?>
<!DOCTYPE superEntry SYSTEM "2007nn.dtd">

<superEntry>
	<orth>철사</orth>
	<entry n="1" pos="nng_s">
		<mnt_grp>
			<cre>
				<cre_date>2000/09/20</cre_date>
				<cre_writer>송근영</cre_writer>
				<cre_note></cre_note>
			</cre>
			<mod>
				<mod_date>2003/03/24</mod_date>
				<mod_writer>이성헌</mod_writer>
				<mod_note></mod_note>
			</mod>
			<mod>
				<mod_date>2006/07/06</mod_date>
				<mod_writer>백고운</mod_writer>                
                 <mod_note>동사정보를 add에서 comb_v로 이동</mod_note>
                 <mod_note>동사정보추가</mod_note>
            </mod>
            <mod>
				<mod_date>2006/11/15</mod_date>
				<mod_writer>김미현</mod_writer>
				<mod_note></mod_note>
			</mod>
                        <mod>
                                <mod_date>2007/08/05</mod_date>
                                <mod_writer>박진희</mod_writer>
                                <mod_note></mod_note>
                        </mod>
			<note>2000/09/30(박동호)</note>
			<note>2003/02/13(서진숙)</note>
			<note>2003/03/24(이성헌)cl에 '가닥|줄'기재</note>
			<note>comb_v의 내용을 add로 이동</note>
			<add></add>
			
			<mod>
				<mod_date>2009/11/01</mod_date>
				<mod_writer>김민호</mod_writer>
				<mod_note>UTF-8로 변경, XML 태그 오류 수정</mod_note>
			</mod>
		</mnt_grp>
		<see></see>
		<morph_grp>
			<var type="temp"></var>
			<str type="N_N">철+사</str>
			<org lg="si">鐵絲</org>
			<hom exist="temp"></hom>
			<der pos="temp" type="temp"></der>
			<comp pos="n" type="suffix">~줄</comp>
			<metc pos="temp" type="temp"></metc>
			<img type="temp"></img>
		</morph_grp>
		<idm_grp>
			<idm type="temp"></idm>
		</idm_grp>
		<sense n="1">
			<sem_grp>
				<eg>~를 구부려서 이런 모양을 만들어 봐.</eg>
				<eg>~로 만든 그물은 무겁지만 튼튼했다.</eg>
				<trans>wire</trans>
				<domain></domain>
				<reg></reg>
				<con></con>
				<curs type="U"/>
				<sem_class>줄</sem_class>
				<lr>
					<syn type="etc">쇠줄</syn>
					<syn type="etc">철선</syn>
					<ant type="temp"></ant>
					<rel>철</rel>
					<rel>펜치</rel>
				</lr>
			</sem_grp>
			<syn_grp>
				<comb_aj type="appr">~가 가늘다</comb_aj>
				<comb_aj type="appr">~가 굵다</comb_aj>
				<comb_aj type="appr">~가 길다</comb_aj>
				<comb_aj type="appr">~가 짧다</comb_aj>
				<comb_n type="temp"></comb_n>
				<comb_v type="narg_vpred">
					<form vcompound="no">~가 끊어지다</form>
					<frame></frame>
				</comb_v>
				<comb_v type="narg_vpred">
					<form vcompound="no">~로 묶다</form>
					<frame></frame>
				</comb_v>
				<comb_v type="narg_vpred">
					<form vcompound="no">~로 매다</form>
					<frame></frame>
				</comb_v>
				<comb_v type="narg_vpred">
					<form vcompound="no">~로 고정하다</form>
					<frame></frame>
				</comb_v>
				<comb_v type="narg_vpred">
					<form vcompound="no">~를 구부리다</form>
					<frame></frame>
				</comb_v>
				<comb_v type="narg_vpred">
					<form vcompound="no">~를 펴다</form>
					<frame></frame>
				</comb_v>
				<comb_v type="narg_vpred">
					<form vcompound="no">~를 감다</form>
					<frame></frame>
				</comb_v>
				<comb_v type="narg_vpred">
					<form vcompound="no">~를 자르다</form>
					<frame></frame>
				</comb_v>
				<comb_v type="narg_vpred">
					<form vcompound="no">~를 잇다</form>
					<frame></frame>
				</comb_v>
				<max_n_str></max_n_str>
				<sel_rst arg="temp"></sel_rst>
				<cl type="uni">가닥</cl>
				<cl type="uni">줄</cl>
				<prt></prt>
				<av></av>
				<pre_d/>
				<pre_n/>
				<s_n/>
			</syn_grp>
		</sense>
	</entry>
</superEntry>
