<?xml version="1.0" encoding="utf-8" standalone="no"?>
<!DOCTYPE superEntry SYSTEM "vv.dtd">
<superEntry>
	<orth>방목하다</orth>
	<entry n="1" pos="vv">
		<mnt_grp>
			<cre>
				<cre_date>2003/11/01</cre_date>
				<cre_writer>허용</cre_writer>
				<cre_writer>박영준</cre_writer>
			</cre>
			<mod>
				<mod_date>2003/11/01</mod_date>
			</mod>
			<mod>
				<mod_date>2005/09/15</mod_date>
				<mod_writer>박보연</mod_writer>
			</mod>
			<mod>
				<mod_date>2009/11/01</mod_date>
				<mod_writer>김민호</mod_writer>
				<mod_note>UTF-8로 변경, XML 태그 오류 수정</mod_note>
			</mod>
		</mnt_grp>
		<morph_grp>
			<var type="spr">방목을 하다</var>
			<cntr opt="opt" type="VDelCCon"/>
			<org lg="si">放牧_</org>
			<infl type="yeo"/>
		</morph_grp>
		<sense n="01">
			<sem_grp>
				<sem_class>방식행위</sem_class>
				<trans>pasture</trans>
				<lr>
					<rel>풀어놓고기르다</rel>
				</lr>
			</sem_grp>
			<frame_grp type="FTR">
				<frame>X=N0-이 Y=N1-을 V</frame>
				<subsense>
					<sel_rst arg="X" tht="AGT">인간</sel_rst>
					<sel_rst arg="Y" tht="THM">동물(가축)</sel_rst>
					<eg>여기는 소를 방목하기 적합한 곳이니 여기에서 목장이나 하나 운영할까?</eg>
					<eg>좁은 면적에 너무 많은 소를 방목하면 좋지 않다.</eg>
				</subsense>
			</frame_grp>
		</sense>
	</entry>
</superEntry>
