<?xml version="1.0" encoding="utf-8" standalone="no"?>
<!DOCTYPE superEntry SYSTEM "vv.dtd">
<superEntry>
	<orth>조직화하다</orth>
	<entry n="1" pos="vv">
		<mnt_grp>
			<cre>
				<cre_date>2002/04/28</cre_date>
				<cre_writer>박철우</cre_writer>
			</cre>
			<mod>
				<mod_date>2002/05/26</mod_date>
				<mod_writer>한선혜</mod_writer>
			</mod>
			<mod>
				<mod_date>2003/07/31</mod_date>
				<mod_writer>노윤채</mod_writer>
			</mod>
			<note>2002/05/14(노윤채)</note>
			<note>2002/05/26(한선혜)헤드그룹, 형태정보그룹 오류 수정</note>
			<note>선택제약, 예문 수정</note>
			<mod>
				<mod_date>2009/11/01</mod_date>
				<mod_writer>김민호</mod_writer>
				<mod_note>UTF-8로 변경, XML 태그 오류 수정</mod_note>
			</mod>
		</mnt_grp>
		<morph_grp>
			<var type="spr">조직화를 하다</var>
			<cntr opt="opt" type="VDelCCon"/>
			<org lg="si">組織化_</org>
			<infl type="yeo"/>
		</morph_grp>
		<sense n="01">
			<sem_grp>
				<sem_class>결과행위</sem_class>
				<trans>organizesystematize</trans>
			</sem_grp>
			<frame_grp type="FTR">
				<frame>X=N0-이 Y=N1-을 V</frame>
				<subsense>
					<sel_rst arg="X" tht="AGT">인간|인간집단</sel_rst>
					<sel_rst arg="Y" tht="THM">인간|인간집단|추상적대상|사회갈등|모임회의|운동대회</sel_rst>
					<eg>시민 연합은 그들의 활동을 점차 조직화해 가고 있다</eg>
					<eg>이 공장은 생산 과정을 조직화함으로써 생산비의 감소와 노동 능률의 향상이라는 알찬 결과를 얻게 되었다</eg>
				</subsense>
			</frame_grp>
		</sense>
	</entry>
</superEntry>
