<?xml version="1.0" encoding="utf-8" standalone="no"?>
<!DOCTYPE superEntry SYSTEM "vv.dtd">
<superEntry>
	<orth>침범하다</orth>
	<entry n="1" pos="vv">
		<mnt_grp>
			<cre>
				<cre_date></cre_date>
				<cre_writer>???</cre_writer>
			</cre>
			<mod>
				<mod_date>2003/10/14</mod_date>
				<mod_writer>한선혜</mod_writer>
			</mod>
			<mod>
				<mod_date>2006/07/10</mod_date>
				<mod_writer>박진호</mod_writer>
			</mod>
			<mod>
				<mod_date>2009/11/01</mod_date>
				<mod_writer>김민호</mod_writer>
				<mod_note>UTF-8로 변경, XML 태그 오류 수정</mod_note>
			</mod>
		</mnt_grp>
		<morph_grp>
			<cntr opt="opt" type="VDelCCon"/>
			<str>N.하</str>
			<org lg="si">侵犯_</org>
			<infl type="yeo"/>
		</morph_grp>
		<sense n="01">
			<sem_grp>
				<sem_class>범죄및비행</sem_class>
				<trans>intrude</trans>
				<trans>trespass</trans>
			</sem_grp>
			<frame_grp type="FIT">
				<frame>X=N0-이 Y=N1-을|에 V</frame>
				<subsense>
					<sel_rst arg="X" tht="AGT">인간</sel_rst>
					<sel_rst arg="Y" tht="LOC">장소(국가|영토)|(영역|경계|범위)</sel_rst>
					<eg>절대 우리 땅을 침범하지 마라.</eg>
					<eg>국적 불명의 비행기가 우리 영공을 침범하였습니다.</eg>
					<eg>남해안에 왜적이 침범하여 도적질을 해가고 있다고 합니다.</eg>
				</subsense>
			</frame_grp>
		</sense>
		<sense n="02">
			<sem_grp>
				<sem_class>범죄및비행</sem_class>
				<trans>violate</trans>
				<trans>infringe</trans>
			</sem_grp>
			<frame_grp type="FTR">
				<frame>X=N0-이 Y=N1-을 V</frame>
				<subsense>
					<sel_rst arg="X" tht="AGT">인간</sel_rst>
					<sel_rst arg="Y" tht="THM">추상적대상(사생활|인권)</sel_rst>
					<eg>남의 사생활을 침범하지 않도록 조심하세요.</eg>
					<eg>이민국에서 이민자들의 인권을 침범하는 사례가 많이 있다.</eg>
				</subsense>
			</frame_grp>
		</sense>
	</entry>
</superEntry>
