<?xml version="1.0" encoding="utf-8" standalone="no"?>
<!DOCTYPE superEntry SYSTEM "vv.dtd">
<superEntry>
	<orth>묘연하다</orth>
	<entry n="1" pos="va">
		<mnt_grp>
			<cre>
				<cre_date>2003/10/23</cre_date>
				<cre_writer>박철우</cre_writer>
			</cre>
			<mod>
				<mod_date>2003/10/23</mod_date>
				<mod_writer>김윤신</mod_writer>
			</mod>
			<mod>
				<mod_date>2006/09/16</mod_date>
				<mod_writer>김민선</mod_writer>
				<mod_note>내부구조 기술</mod_note>
				<mod_note>영어대역어 수정</mod_note>
				<mod_note>어휘의미관계 보충</mod_note>
				<mod_note>격틀 수정</mod_note>
			</mod>
			<mod>
				<mod_date>2009/11/01</mod_date>
				<mod_writer>김민호</mod_writer>
				<mod_note>UTF-8로 변경, XML 태그 오류 수정</mod_note>
			</mod>
		</mnt_grp>
		<morph_grp>
			<var type="etc"></var>
			<str>R.하</str>
			<org lg="si">杳然_</org>
		</morph_grp>
		<sense n="01">
			<sem_grp>
				<sem_class></sem_class>
				<trans>be faraway</trans>
				<trans>be remote</trans>
				<lr>
					<syn type="perfect">묘원하다</syn>
					<syn type="kor">아득하다</syn>
					<ant type="grad">가깝다</ant>
				</lr>
			</sem_grp>
			<frame_grp type="FA">
				<frame>X=N0-이 A</frame>
				<subsense>
					<sel_rst arg="X" tht="THM">구체물|장소</sel_rst>
					<eg>산길이 너무 험하고 길어서 정상에 이르는 길이 묘연했다.</eg>
					<eg>외항선을 타는 선원들은 묘연한 바다를 바라보며 향수에 젖곤 한다.</eg>
				</subsense>
			</frame_grp>
		</sense>
		<sense n="02">
			<sem_grp>
				<sem_class></sem_class>
				<trans>be dim</trans>
				<trans>be vague</trans>
				<trans>be indistinct</trans>
				<lr>
					<syn type="perfect">희미하다</syn>
					<syn type="kor">가물가물하다</syn>
					<syn type="kor">흐릿하다</syn>
					<ant type="grad">또렷하다</ant>
				</lr>
			</sem_grp>
			<frame_grp type="FA">
				<frame>X=N0-이 Y=N1-이 A</frame>
				<subsense>
					<sel_rst arg="X" tht="EXP">인간</sel_rst>
					<sel_rst arg="Y" tht="THM">인간|인간집단|인지상태</sel_rst>
					<eg>오랜만에 내가 다녔던 초등학교를 찾았지만 너무나 많이 달라져서 그 시절 그 추억이 묘연했다.</eg>
					<eg>이제는 십수 년이 지난 일이라 나는 이제 첫사랑의 기억조차 묘연하다.</eg>
				</subsense>
			</frame_grp>
		</sense>
		<sense n="03">
			<sem_grp>
				<sem_class></sem_class>
				<trans>be utterly unknown</trans>
				<lr>
					<syn type="kor">자취없다</syn>
					<ant type="compl">분명하다</ant>
				</lr>
			</sem_grp>
			<frame_grp type="FA">
				<frame>X=N0-이 A</frame>
				<subsense>
					<sel_rst arg="X" tht="THM">인간|구체물|(소식|행방|종적)</sel_rst>
					<eg>중기는 계속해서 영득이를 찾았지만 그의 행방이 묘연했다.</eg>
					<eg>반란은 실패했고 반란의 우두머리는 행방이 묘연했었다.</eg>
					<eg>비행기 추락사고 이후에 사고의 원인에 대한 유일한 단서인 블랙박스의 행방이 묘연해 사람들의 관심이 집중되고 있다.</eg>
				</subsense>
			</frame_grp>
		</sense>
	</entry>
	<entry n="2" pos="va">
		<mnt_grp>
			<cre>
				<cre_date>2003/10/23</cre_date>
				<cre_writer>박철우</cre_writer>
			</cre>
			<mod>
				<mod_date>2003/10/23</mod_date>
				<mod_writer>김윤신</mod_writer>
			</mod>
			<mod>
				<mod_date>2006/09/16</mod_date>
				<mod_writer>김민선</mod_writer>
				<mod_note>내부구조 기술</mod_note>
				<mod_note>영어대역어 수정</mod_note>
				<mod_note>어휘의미관계 보충</mod_note>
				<mod_note>두 번째 센스 격틀 수정</mod_note>
			</mod>
			<mod>
				<mod_date>2009/11/01</mod_date>
				<mod_writer>김민호</mod_writer>
				<mod_note>UTF-8로 변경, XML 태그 오류 수정</mod_note>
			</mod>
		</mnt_grp>
		<morph_grp>
			<var type="etc"></var>
			<str>R.하</str>
			<org lg="si">渺然_</org>
		</morph_grp>
		<sense n="01">
			<sem_grp>
				<sem_class></sem_class>
				<trans>be faraway</trans>
				<trans>be remote</trans>
				<lr>
					<syn type="perfect">묘원하다</syn>
					<syn type="kor">아득하다</syn>
					<ant type="grad">가깝다</ant>
				</lr>
			</sem_grp>
			<frame_grp type="FA">
				<frame>X=N0-이 A</frame>
				<subsense>
					<sel_rst arg="X" tht="LOC">장소</sel_rst>
					<eg>아득하고 묘연한 고향하늘을 생각하면 눈물이 절로 난다.</eg>
					<eg>무인도에 표류하여 홀로 살아가고 있던 그 남자에게는 묘연한 바다를 바라보는 것이 중요한 일과였다.</eg>
				</subsense>
			</frame_grp>
		</sense>
	</entry>
</superEntry>
