<?xml version="1.0" encoding="utf-8" standalone="no"?>
<!DOCTYPE superEntry SYSTEM "vv.dtd">
<superEntry>
	<orth>무감하다</orth>
	<entry n="1" pos="va">
		<mnt_grp>
			<cre>
				<cre_date>2003/08/29</cre_date>
				<cre_writer>김현권</cre_writer>
				<cre_writer>조현경</cre_writer>
			</cre>
			<mod>
				<mod_date>2003/08/29</mod_date>
			</mod>
			<mod>
				<mod_date>2006/07/04</mod_date>
				<mod_writer>박보연</mod_writer>
			</mod>
			<mod>
				<mod_date>2009/11/01</mod_date>
				<mod_writer>김민호</mod_writer>
				<mod_note>UTF-8로 변경, XML 태그 오류 수정</mod_note>
			</mod>
		</mnt_grp>
		<morph_grp>
			<cntr opt="opt" type="VDelCCon"/>
			<org lg="si">無感_</org>
			<infl type="yeo"/>
		</morph_grp>
		<sense n="01">
			<sem_grp>
				<sem_class></sem_class>
				<trans>insensible</trans>
				<trans>senseless</trans>
				<trans>callous</trans>
			</sem_grp>
			<frame_grp type="FA">
				<frame>X=N0-이 Y=N1-에|에대해 A</frame>
				<subsense>
					<sel_rst arg="X" tht="EXP">인간|인간집단</sel_rst>
					<sel_rst arg="Y" tht="THM">온</sel_rst>
					<eg>그의 어머니는 다른 어머니들과는 다르게 자식의 행동에 무감하다.</eg>
					<eg>그 많은 승객들이 모두 버스의 엔진상태에 무감했었다.</eg>
				</subsense>
				<subsense>
					<sel_rst arg="X" tht="AGT">인간|인간집단</sel_rst>
					<sel_rst arg="Y" tht="THM">S는것|S데</sel_rst>
					<eg>순이아빠는 순이가 길거리에 넘어져서 다리를 다친 것에도 무감하다.</eg>
					<eg>아이들에게 질린 경비실아저씨는 아이들이 싸우는 데에도 무감하기로 했다.</eg>
				</subsense>
			</frame_grp>
		</sense>
	</entry>
</superEntry>
