<?xml version="1.0" encoding="utf-8" standalone="no"?>
<!DOCTYPE superEntry SYSTEM "vv.dtd">
<superEntry>
	<orth>미성숙하다</orth>
	<entry n="1" pos="va">
		<mnt_grp>
			<cre>
				<cre_date>2003/10/15</cre_date>
				<cre_writer>허용</cre_writer>
				<cre_writer>박영준</cre_writer>
			</cre>
			<mod>
				<mod_date>2003/10/15</mod_date>
			</mod>
			<mod>
				<mod_date>2006/07/04</mod_date>
				<mod_writer>박보연</mod_writer>
			</mod>
			<mod>
				<mod_date>2009/11/01</mod_date>
				<mod_writer>김민호</mod_writer>
				<mod_note>UTF-8로 변경, XML 태그 오류 수정</mod_note>
			</mod>
		</mnt_grp>
		<morph_grp>
			<cntr opt="opt" type="VDelCCon"/>
			<org lg="si">未成熟_</org>
			<infl type="yeo"/>
		</morph_grp>
		<sense n="01">
			<sem_grp>
				<sem_class></sem_class>
				<trans>be unripe</trans>
				<trans>immature</trans>
			</sem_grp>
			<frame_grp type="FA">
				<frame>X=N0-이 A</frame>
				<subsense>
					<sel_rst arg="X" tht="THM">인간|동물</sel_rst>
					<eg>인간은 미성숙하기 때문에 성장이 가능하다.</eg>
					<eg>미성숙한 어린이는 다른 사람을 의식해야 하는 필요성을 미처 느끼지 못한다.</eg>
				</subsense>
				<subsense>
					<sel_rst arg="X" tht="THM">속성(정신)|사태(행동|말)</sel_rst>
					<eg>선진국의 부모와 선생님은 아이들이 떼쓰는 것과 같은 미성숙한 행동과 부정부패를 유발하는 부정직한 행동에 대해 매우 철저하게 통제하고 교육하고 있다.</eg>
					<eg>아동의 그림에서 전체적으로 정서적, 지적수준이 미성숙하고 사회성이 부족함을 알수 있다.</eg>
				</subsense>
			</frame_grp>
		</sense>
	</entry>
</superEntry>
