<?xml version="1.0" encoding="utf-8" standalone="no"?>
<!DOCTYPE superEntry SYSTEM "vv.dtd">
<superEntry>
	<orth>짱짱하다</orth>
	<entry n="1" pos="va">
		<mnt_grp>
			<cre>
				<cre_date>2003/10/13</cre_date>
				<cre_writer>강정연</cre_writer>
				<cre_writer>김현권</cre_writer>
			</cre>
			<mod>
				<mod_date>2005/08/03</mod_date>
				<mod_writer>김종명</mod_writer>
			</mod>
			<mod>
				<mod_date>2009/11/01</mod_date>
				<mod_writer>김민호</mod_writer>
				<mod_note>UTF-8로 변경, XML 태그 오류 수정</mod_note>
			</mod>
		</mnt_grp>
		<morph_grp>
			<var type="etc"></var>
			<cntr opt="opt" type="VDelCCon"/>
			<str></str>
			<infl type="yeo"/>
		</morph_grp>
		<sense n="01">
			<sem_grp>
				<sem_class></sem_class>
				<trans>be solid</trans>
			</sem_grp>
			<frame_grp type="FA">
				<frame>X=N0-이 A</frame>
				<subsense>
					<sel_rst arg="X" tht="THM">구체물|추상적대상(모습)</sel_rst>
					<eg>그의 모습 아주 짱짱했다.</eg>
					<eg>할아버지는 기력이 아직도 짱짱하시다.</eg>
				</subsense>
			</frame_grp>
		</sense>
		<sense n="02">
			<sem_grp>
				<sem_class></sem_class>
				<trans>be good</trans>
				<lr>
					<syn type="vulgar">빵빵하다</syn>
				</lr>
			</sem_grp>
			<frame_grp type="FA">
				<frame>X=N0-이 A</frame>
				<subsense>
					<sel_rst arg="X" tht="THM">추상적대상(집안)|추상적대상(실력)</sel_rst>
					<eg>그 아이들은 다들 집안들이 짱짱하다.</eg>
					<eg>그 사람들은 영어 구사 능력이 다들 짱짱하다.</eg>
				</subsense>
			</frame_grp>
		</sense>
		<sense n="02">
			<sem_grp>
				<sem_class></sem_class>
				<trans>be spotless</trans>
				<trans>be perfect</trans>
				<lr>
					<syn type="perfect">뭘쩡하다</syn>
					<syn type="sino">온전하다</syn>
				</lr>
			</sem_grp>
			<frame_grp type="FA">
				<frame>X=N0-이 A</frame>
				<subsense>
					<sel_rst arg="X" tht="THM">구체물</sel_rst>
					<eg>뭐 내가 보기에는 이 컴퓨터 아직도 짱짱한데.</eg>
				</subsense>
			</frame_grp>
		</sense>
	</entry>
</superEntry>
